examples/sample.v
module ATE(clk,reset,pix_data,type,bin,threshold);
input clk;
input reset;
input [7:0] pix_data;
input type;
output bin;
output [7:0] threshold;
reg [7:0] threshold;
reg bin;

// ================= IDENTIFIER =================
reg [6:0] col; //column
reg [5:0] Counter; //internal counter
reg [12:0]block_count; //block counter
reg en, state;
reg [1:0]cs,ns;
wire _en, _bin, z, _delay;
wire [6:0] _col, c_bound;
wire [5:0] _Counter;
wire [7:0] _threshold, Thres, Max, Min;
wire [7:0] pix_out;

// ================= Counter / State =================
assign _Counter = Counter + 1'b1;
assign cnt63    = &Counter;  // Counter == 63
assign _state   = (en) ? 1'b1 : state;

// ================= Column control =================
assign c_bound  = (type) ? 7'd65 : 7'd5;
assign _col     = (en && state) ? ((col == c_bound) ? 7'd0 : col + 1'b1) : col;

// ================= Boundary detect =================
assign z        = (col == c_bound) || (~|col);

// ================= Output generation =================
assign _bin       = (z) ? 1'b0 : (pix_out >= Thres);
assign _threshold = (z) ? 8'd0 : Thres;

// ================= SEQUENTIAL =================
always @(posedge clk or posedge reset) begin
    if (reset) begin
        Counter   <= 6'd0;
        state     <= 1'b0;
        en        <= 1'b0;
        col       <= 7'd0;
        threshold <= 8'd0;
        bin       <= 1'b0;
    end
    else begin
        Counter   <= _Counter;
        state     <= _state;
        en        <= cnt63;
        col       <= _col;
        threshold <= _threshold;
        bin       <= _bin;
    end
end
// ================= SUBMODULES =================
FIFO_64 F1(.clk(clk),.pix_data(pix_data),.Addr(Counter),.pix_out(pix_out));
MAX_MIN  mm0(pix_data, clk, reset, Counter, Max, Min);
THRES_GEN th0(Max, Min, clk, reset, en, Thres);
endmodule

/*=================MAX_MIN=================*/
module MAX_MIN (
    input [7:0] pix_data,
    input clk,
    input reset,
    input [5:0] cnt,      
    output reg [7:0] Max,
    output reg [7:0] Min
);

always @(posedge clk or posedge reset) begin
    if (reset) begin
        Max <= 8'd0;
        Min <= 8'd0; 
        
    end
    else begin

        if (cnt == 6'd0) begin
            Max <= pix_data;
            Min <= pix_data;
        end
      
        else begin
 
            if (pix_data > Max) 
                Max <= pix_data;
            
        
            if (pix_data < Min) 
                Min <= pix_data;
        end
    end
end

endmodule

/*=================FIFO_64=================*/
module FIFO_64(pix_data, clk, Addr ,pix_out);

parameter data_width = 7;
parameter fifo_depth = 63;

input [data_width:0]pix_data;
input clk;
input [5:0] Addr;
output reg[data_width:0]pix_out;


reg [data_width:0]fifo[fifo_depth:0];//8bits*64

always @(posedge clk) begin
	fifo[Addr] <= pix_data;
	pix_out <= fifo[Addr];
end

endmodule

/*=================THRES_GEN (RCA)=================*/
module THRES_GEN (Max, Min, clk, reset, en, Thres);

input	[7:0]	Max, Min;
input clk , reset, en;
output reg [7:0]	Thres;

wire Cin, C_out;
wire [6:0] Cm;
wire [7:0] sum;

assign Cin = Max[0] ^ Min[0]; //小數點進位

FA f0(Max[0], Min[0], Cin  , sum[0], Cm[0]);
FA f1(Max[1], Min[1], Cm[0], sum[1], Cm[1]);
FA f2(Max[2], Min[2], Cm[1], sum[2], Cm[2]);
FA f3(Max[3], Min[3], Cm[2], sum[3], Cm[3]);
FA f4(Max[4], Min[4], Cm[3], sum[4], Cm[4]);
FA f5(Max[5], Min[5], Cm[4], sum[5], Cm[5]);
FA f6(Max[6], Min[6], Cm[5], sum[6], Cm[6]);
FA f7(Max[7], Min[7], Cm[6], sum[7], C_out);

always @(posedge clk or posedge reset) begin
	if(reset)
		Thres <= 8'd0;
	else
		Thres <= (en) ? {C_out, sum[7:1]} : Thres; //0.5 * (Max + Min)
end
endmodule

module FA(a, b, cin, s, cout);
input a, b, cin;
output s, cout;
wire s0, c0, c1;
	HA u0(a, b, s0, c0);
	HA u1(s0, cin, s, c1);
	or g0(cout, c0, c1);
endmodule

module HA(a, b, s, cout);
input a, b;
output s, cout;
	and g0(cout,a,b);
	xor g1(s, a, b);
endmodule

examples/sample_tb.v
`timescale 1ns / 1ps

//================================================================================
// Testbench for ATE Module
// 此測試台用於驗證 ATE 模組的功能
// 測試資料來源：tb1.map（4096 筆 8-bit 十六進位數據）
//================================================================================

module sample_tb;

    //============================================================================
    // 訊號宣告
    //============================================================================
    
    // 時脈與重置訊號
    reg clk;
    reg reset;
    
    // ATE 模組的輸入訊號
    reg [7:0] pix_data;      // 8-bit 像素資料輸入
    reg type;                // 類型選擇訊號
    
    // ATE 模組的輸出訊號
    wire bin;                // 二值化輸出
    wire [7:0] threshold;    // 8-bit 閾值輸出
    
    // 測試資料儲存空間
    reg [7:0] test_patterns [0:4095];  // 儲存 4096 筆測試資料
    
    // 迴圈計數器
    integer i;

    //============================================================================
    // 例現化待測模組 (Design Under Test)
    //============================================================================
    
    ATE uut (
        .clk(clk),
        .reset(reset),
        .pix_data(pix_data),
        .type(type),
        .bin(bin),
        .threshold(threshold)
    );

    //============================================================================
    // 時脈產生器
    // 週期：10ns (頻率：100MHz)
    //============================================================================
    
    initial begin
        clk = 1'b0;
    end
    
    always #5 clk = ~clk;  // 每 5ns 反轉一次，形成 10ns 週期

    //============================================================================
    // 測試主程式
    //============================================================================
    
    initial begin
        // VCD 波形檔案輸出設定（Stage 3 模擬分析所需）
        $dumpfile("dump.vcd");
        $dumpvars(0, sample_tb);
        
        // 顯示測試開始訊息
        $display("========================================");
        $display("ATE Module Testbench");
        $display("開始時間：%0t ns", $time);
        $display("========================================");
        
        // 讀取測試資料（十六進位格式）
        $readmemh("tb1.map", test_patterns);
        $display("已載入測試資料：tb1.map (4096 筆)");
        
        // 初始化所有輸入訊號
        reset = 1'b1;        // 啟動重置
        pix_data = 8'h00;    // 像素資料初始化為 0
        type = 1'b0;         // 類型訊號初始化為 0
        
        // 維持重置訊號 20ns
        #20;
        reset = 1'b0;        // 釋放重置
        $display("重置完成，開始餵入測試資料 (%0t ns)", $time);
        
        // 等待一個時脈週期讓系統穩定
        @(posedge clk);
        
        // 依序將 4096 個像素資料餵給 ATE 模組
        for (i = 0; i < 4096; i = i + 1) begin
            @(posedge clk);  // 在時脈上升緣更新資料
            pix_data = test_patterns[i];
            
            // 每 512 筆資料顯示一次進度
            if (i % 512 == 0) begin
                $display("進度：%0d / 4096 筆資料已送出 (%0t ns)", i, $time);
            end
        end
        
        // 所有資料送出完畢
        $display("========================================");
        $display("測試資料送出完成：4096 筆");
        $display("完成時間：%0t ns", $time);
        $display("========================================");
        
        // 額外等待 100ns 讓所有訊號穩定
        #100;
        
        // 結束模擬
        $display("模擬結束");
        $finish;
    end
    
    //============================================================================
    // 監控與除錯（選用）
    //============================================================================
    
    // 監控關鍵訊號變化
    initial begin
        $monitor("時間=%0t | pix_data=%h | bin=%b | threshold=%h", 
                 $time, pix_data, bin, threshold);
    end

endmodule

examples/dump.vcd
$date
	Tue Mar 10 16:35:19 2026
$end
$version
	Icarus Verilog
$end
$timescale
	1ps
$end
$scope module sample_tb $end
$var wire 8 ! threshold [7:0] $end
$var wire 1 " bin $end
$var reg 1 # clk $end
$var reg 8 $ pix_data [7:0] $end
$var reg 1 % reset $end
$var reg 1 & type $end
$var integer 32 ' i [31:0] $end
$scope module uut $end
$var wire 1 # clk $end
$var wire 8 ( pix_data [7:0] $end
$var wire 1 % reset $end
$var wire 1 & type $end
$var wire 1 ) z $end
$var wire 8 * pix_out [7:0] $end
$var wire 1 + cnt63 $end
$var wire 7 , c_bound [6:0] $end
$var wire 8 - _threshold [7:0] $end
$var wire 1 . _state $end
$var wire 7 / _col [6:0] $end
$var wire 1 0 _bin $end
$var wire 6 1 _Counter [5:0] $end
$var wire 8 2 Thres [7:0] $end
$var wire 8 3 Min [7:0] $end
$var wire 8 4 Max [7:0] $end
$var reg 6 5 Counter [5:0] $end
$var reg 1 " bin $end
$var reg 7 6 col [6:0] $end
$var reg 1 7 en $end
$var reg 1 8 state $end
$var reg 8 9 threshold [7:0] $end
$scope module F1 $end
$var wire 6 : Addr [5:0] $end
$var wire 1 # clk $end
$var wire 8 ; pix_data [7:0] $end
$var parameter 32 < data_width $end
$var parameter 32 = fifo_depth $end
$var reg 8 > pix_out [7:0] $end
$upscope $end
$scope module mm0 $end
$var wire 1 # clk $end
$var wire 6 ? cnt [5:0] $end
$var wire 8 @ pix_data [7:0] $end
$var wire 1 % reset $end
$var reg 8 A Max [7:0] $end
$var reg 8 B Min [7:0] $end
$upscope $end
$scope module th0 $end
$var wire 1 C Cin $end
$var wire 8 D Max [7:0] $end
$var wire 8 E Min [7:0] $end
$var wire 1 # clk $end
$var wire 1 7 en $end
$var wire 1 % reset $end
$var wire 8 F sum [7:0] $end
$var wire 7 G Cm [6:0] $end
$var wire 1 H C_out $end
$var reg 8 I Thres [7:0] $end
$scope module f0 $end
$var wire 1 J a $end
$var wire 1 K b $end
$var wire 1 C cin $end
$var wire 1 L cout $end
$var wire 1 M s0 $end
$var wire 1 N s $end
$var wire 1 O c1 $end
$var wire 1 P c0 $end
$scope module u0 $end
$var wire 1 J a $end
$var wire 1 K b $end
$var wire 1 P cout $end
$var wire 1 M s $end
$upscope $end
$scope module u1 $end
$var wire 1 M a $end
$var wire 1 C b $end
$var wire 1 O cout $end
$var wire 1 N s $end
$upscope $end
$upscope $end
$scope module f1 $end
$var wire 1 Q a $end
$var wire 1 R b $end
$var wire 1 S cin $end
$var wire 1 T cout $end
$var wire 1 U s0 $end
$var wire 1 V s $end
$var wire 1 W c1 $end
$var wire 1 X c0 $end
$scope module u0 $end
$var wire 1 Q a $end
$var wire 1 R b $end
$var wire 1 X cout $end
$var wire 1 U s $end
$upscope $end
$scope module u1 $end
$var wire 1 U a $end
$var wire 1 S b $end
$var wire 1 W cout $end
$var wire 1 V s $end
$upscope $end
$upscope $end
$scope module f2 $end
$var wire 1 Y a $end
$var wire 1 Z b $end
$var wire 1 [ cin $end
$var wire 1 \ cout $end
$var wire 1 ] s0 $end
$var wire 1 ^ s $end
$var wire 1 _ c1 $end
$var wire 1 ` c0 $end
$scope module u0 $end
$var wire 1 Y a $end
$var wire 1 Z b $end
$var wire 1 ` cout $end
$var wire 1 ] s $end
$upscope $end
$scope module u1 $end
$var wire 1 ] a $end
$var wire 1 [ b $end
$var wire 1 _ cout $end
$var wire 1 ^ s $end
$upscope $end
$upscope $end
$scope module f3 $end
$var wire 1 a a $end
$var wire 1 b b $end
$var wire 1 c cin $end
$var wire 1 d cout $end
$var wire 1 e s0 $end
$var wire 1 f s $end
$var wire 1 g c1 $end
$var wire 1 h c0 $end
$scope module u0 $end
$var wire 1 a a $end
$var wire 1 b b $end
$var wire 1 h cout $end
$var wire 1 e s $end
$upscope $end
$scope module u1 $end
$var wire 1 e a $end
$var wire 1 c b $end
$var wire 1 g cout $end
$var wire 1 f s $end
$upscope $end
$upscope $end
$scope module f4 $end
$var wire 1 i a $end
$var wire 1 j b $end
$var wire 1 k cin $end
$var wire 1 l cout $end
$var wire 1 m s0 $end
$var wire 1 n s $end
$var wire 1 o c1 $end
$var wire 1 p c0 $end
$scope module u0 $end
$var wire 1 i a $end
$var wire 1 j b $end
$var wire 1 p cout $end
$var wire 1 m s $end
$upscope $end
$scope module u1 $end
$var wire 1 m a $end
$var wire 1 k b $end
$var wire 1 o cout $end
$var wire 1 n s $end
$upscope $end
$upscope $end
$scope module f5 $end
$var wire 1 q a $end
$var wire 1 r b $end
$var wire 1 s cin $end
$var wire 1 t cout $end
$var wire 1 u s0 $end
$var wire 1 v s $end
$var wire 1 w c1 $end
$var wire 1 x c0 $end
$scope module u0 $end
$var wire 1 q a $end
$var wire 1 r b $end
$var wire 1 x cout $end
$var wire 1 u s $end
$upscope $end
$scope module u1 $end
$var wire 1 u a $end
$var wire 1 s b $end
$var wire 1 w cout $end
$var wire 1 v s $end
$upscope $end
$upscope $end
$scope module f6 $end
$var wire 1 y a $end
$var wire 1 z b $end
$var wire 1 { cin $end
$var wire 1 | cout $end
$var wire 1 } s0 $end
$var wire 1 ~ s $end
$var wire 1 !" c1 $end
$var wire 1 "" c0 $end
$scope module u0 $end
$var wire 1 y a $end
$var wire 1 z b $end
$var wire 1 "" cout $end
$var wire 1 } s $end
$upscope $end
$scope module u1 $end
$var wire 1 } a $end
$var wire 1 { b $end
$var wire 1 !" cout $end
$var wire 1 ~ s $end
$upscope $end
$upscope $end
$scope module f7 $end
$var wire 1 #" a $end
$var wire 1 $" b $end
$var wire 1 %" cin $end
$var wire 1 H cout $end
$var wire 1 &" s0 $end
$var wire 1 '" s $end
$var wire 1 (" c1 $end
$var wire 1 )" c0 $end
$scope module u0 $end
$var wire 1 #" a $end
$var wire 1 $" b $end
$var wire 1 )" cout $end
$var wire 1 &" s $end
$upscope $end
$scope module u1 $end
$var wire 1 &" a $end
$var wire 1 %" b $end
$var wire 1 (" cout $end
$var wire 1 '" s $end
$upscope $end
$upscope $end
$upscope $end
$upscope $end
$upscope $end
$enddefinitions $end
$comment Show the parameter values. $end
$dumpall
b111111 =
b111 <
$end
#0
$dumpvars
0)"
0("
0'"
0&"
0%"
0$"
0#"
0""
0!"
0~
0}
0|
0{
0z
0y
0x
0w
0v
0u
0t
0s
0r
0q
0p
0o
0n
0m
0l
0k
0j
0i
0h
0g
0f
0e
0d
0c
0b
0a
0`
0_
0^
0]
0\
0[
0Z
0Y
0X
0W
0V
0U
0T
0S
0R
0Q
0P
0O
0N
0M
0L
0K
0J
b0 I
0H
b0 G
b0 F
b0 E
b0 D
0C
b0 B
b0 A
b0 @
b0 ?
bx >
b0 ;
b0 :
b0 9
08
07
b0 6
b0 5
b0 4
b0 3
b0 2
b1 1
00
b0 /
0.
b0 -
b101 ,
0+
bx *
1)
b0 (
bx '
0&
1%
b0 $
0#
0"
b0 !
$end
#5000
1#
#10000
0#
#15000
b0 *
b0 >
1#
#20000
0#
0%
#25000
b10 1
b1 5
b1 :
b1 ?
b0 '
1#
#30000
0#
#35000
bx *
bx >
b11 1
b10 5
b10 :
b10 ?
b1 '
b100100 $
b100100 (
b100100 ;
b100100 @
1#
#40000
0#
#45000
1^
b100100 F
1v
1]
1u
1Y
1q
b100 1
b11 5
b11 :
b11 ?
b100100 4
b100100 A
b100100 D
b10 '
1#
#50000
0#
#55000
b101 1
b100 5
b100 :
b100 ?
b11 '
1#
#60000
0#
#65000
b110 1
b101 5
b101 :
b101 ?
b100 '
1#
#70000
0#
#75000
b111 1
b110 5
b110 :
b110 ?
b101 '
1#
#80000
0#
#85000
b1000 1
b111 5
b111 :
b111 ?
b110 '
1#
#90000
0#
#95000
b1001 1
b1000 5
b1000 :
b1000 ?
b111 '
1#
#100000
0#
#105000
b1010 1
b1001 5
b1001 :
b1001 ?
b1000 '
1#
#110000
0#
#115000
b1011 1
b1010 5
b1010 :
b1010 ?
b1001 '
1#
#120000
0#
#125000
b1100 1
b1011 5
b1011 :
b1011 ?
b1010 '
b101101 $
b101101 (
b101101 ;
b101101 @
1#
#130000
0#
#135000
1V
1S
b1 G
1L
1O
b101110 F
1f
1C
1M
1e
1J
1a
b101101 4
b101101 A
b101101 D
b1101 1
b1100 5
b1100 :
b1100 ?
b1011 '
b110110 $
b110110 (
b110110 ;
b110110 @
1#
#140000
0#
#145000
0c
0\
0_
1^
0S
0[
0L
b0 G
0T
0O
0W
1V
0f
b110110 F
1n
0C
0M
1U
0e
1m
0J
1Q
0a
1i
b1110 1
b1101 5
b1101 :
b1101 ?
b110110 4
b110110 A
b110110 D
b1100 '
b111111 $
b111111 (
b111111 ;
b111111 @
1#
#150000
0#
#155000
1~
1{
1t
1w
0v
1s
1l
1o
0n
1k
1d
1g
1c
1\
1_
0^
1[
1T
1W
0V
1S
b111111 G
1L
1O
b1000000 F
0f
1C
1M
1e
1J
1a
b111111 4
b111111 A
b111111 D
b1111 1
b1110 5
b1110 :
b1110 ?
b1101 '
b1001000 $
b1001000 (
b1001000 ;
b1001000 @
1#
#160000
0#
#165000
0k
0d
0g
1f
0'"
0S
0[
0c
0s
0{
0%"
0L
0T
0\
0l
0t
b0 G
0|
0O
0W
0V
0_
0^
0o
0n
0w
0v
0!"
b1001000 F
1~
0C
0M
0U
0]
0m
0u
1}
0J
0Q
0Y
0i
0q
1y
b10000 1
b1111 5
b1111 :
b1111 ?
b1001000 4
b1001000 A
b1001000 D
b1110 '
b1010000 $
b1010000 (
b1010000 ;
b1010000 @
1#
#170000
0#
#175000
0f
b1010000 F
1n
0e
1m
0a
1i
b1010000 4
b1010000 A
b1010000 D
b10001 1
b10000 5
b10000 :
b10000 ?
b1111 '
b111011 $
b111011 (
b111011 ;
b111011 @
1#
#180000
0#
#185000
b10010 1
b10001 5
b10001 :
b10001 ?
b10000 '
b1100010 $
b1100010 (
b1100010 ;
b1100010 @
1#
#190000
0#
#195000
1V
0n
b1100010 F
1v
1U
0m
1u
1Q
0i
1q
b1100010 4
b1100010 A
b1100010 D
b10011 1
b10010 5
b10010 :
b10010 ?
b10001 '
b1101010 $
b1101010 (
b1101010 ;
b1101010 @
1#
#200000
0#
#205000
b1101010 F
1f
1e
1a
b10100 1
b10011 5
b10011 :
b10011 ?
b1101010 4
b1101010 A
b1101010 D
b10010 '
1#
#210000
0#
#215000
b10101 1
b10100 5
b10100 :
b10100 ?
b10011 '
b1110011 $
b1110011 (
b1110011 ;
b1110011 @
1#
#220000
0#
#225000
1^
1[
1T
1W
0V
1S
b11 G
1L
1O
0f
b1110100 F
1n
1C
1M
0e
1m
1J
0a
1i
b10110 1
b10101 5
b10101 :
b10101 ?
b1110011 4
b1110011 A
b1110011 D
b10100 '
b1111011 $
b1111011 (
b1111011 ;
b1111011 @
1#
#230000
0#
#235000
b1111100 F
1f
1e
1a
b1111011 4
b1111011 A
b1111011 D
b10111 1
b10110 5
b10110 :
b10110 ?
b10101 '
b10000100 $
b10000100 (
b10000100 ;
b10000100 @
1#
#240000
0#
#245000
0S
0[
0c
0L
0T
b0 G
0\
0O
0W
0V
0_
1^
0f
0n
0v
0~
b10000100 F
1'"
0C
0M
0U
1]
0e
0m
0u
0}
1&"
0J
0Q
1Y
0a
0i
0q
0y
1#"
b11000 1
b10111 5
b10111 :
b10111 ?
b10000100 4
b10000100 A
b10000100 D
b10110 '
b10001101 $
b10001101 (
b10001101 ;
b10001101 @
1#
#250000
0#
#255000
1V
1S
b1 G
1L
1O
b10001110 F
1f
1C
1M
1e
1J
1a
b10001101 4
b10001101 A
b10001101 D
b11001 1
b11000 5
b11000 :
b11000 ?
b10111 '
b10010110 $
b10010110 (
b10010110 ;
b10010110 @
1#
#260000
0#
#265000
0c
0\
0_
1^
0S
0[
0L
b0 G
0T
0O
0W
1V
0f
b10010110 F
1n
0C
0M
1U
0e
1m
0J
1Q
0a
1i
b11010 1
b11001 5
b11001 :
b11001 ?
b10010110 4
b10010110 A
b10010110 D
b11000 '
1#
#270000
0#
#275000
b11011 1
b11010 5
b11010 :
b11010 ?
b11001 '
b10011111 $
b10011111 (
b10011111 ;
b10011111 @
1#
#280000
0#
#285000
1v
1s
1l
1o
0n
1k
1d
1g
1c
1\
1_
0^
1[
1T
1W
0V
1S
b11111 G
1L
1O
b10100000 F
0f
1C
1M
1e
1J
1a
b11100 1
b11011 5
b11011 :
b11011 ?
b10011111 4
b10011111 A
b10011111 D
b11010 '
b10100111 $
b10100111 (
b10100111 ;
b10100111 @
1#
#290000
0#
#295000
0~
0k
0s
0{
0d
0l
b111 G
0t
0g
1f
0o
0n
0w
b10101000 F
1v
0e
0m
1u
0a
0i
1q
b10100111 4
b10100111 A
b10100111 D
b11101 1
b11100 5
b11100 :
b11100 ?
b11011 '
1#
#300000
0#
#305000
b11110 1
b11101 5
b11101 :
b11101 ?
b11100 '
b10110000 $
b10110000 (
b10110000 ;
b10110000 @
1#
#310000
0#
#315000
0f
0S
0[
0c
0L
0T
b0 G
0\
0O
0W
0V
0_
0^
b10110000 F
1n
0C
0M
0U
0]
1m
0J
0Q
0Y
1i
b10110000 4
b10110000 A
b10110000 D
b11111 1
b11110 5
b11110 :
b11110 ?
b11101 '
b10111000 $
b10111000 (
b10111000 ;
b10111000 @
1#
#320000
0#
#325000
b10111000 F
1f
1e
1a
b100000 1
b11111 5
b11111 :
b11111 ?
b10111000 4
b10111000 A
b10111000 D
b11110 '
1#
#330000
0#
#335000
b100001 1
b100000 5
b100000 :
b100000 ?
b11111 '
1#
#340000
0#
#345000
b100010 1
b100001 5
b100001 :
b100001 ?
b100000 '
1#
#350000
0#
#355000
b100011 1
b100010 5
b100010 :
b100010 ?
b100001 '
1#
#360000
0#
#365000
b100100 1
b100011 5
b100011 :
b100011 ?
b100010 '
1#
#370000
0#
#375000
b100101 1
b100100 5
b100100 :
b100100 ?
b100011 '
1#
#380000
0#
#385000
b100110 1
b100101 5
b100101 :
b100101 ?
b100100 '
1#
#390000
0#
#395000
b100111 1
b100110 5
b100110 :
b100110 ?
b100101 '
1#
#400000
0#
#405000
b101000 1
b100111 5
b100111 :
b100111 ?
b100110 '
b10110000 $
b10110000 (
b10110000 ;
b10110000 @
1#
#410000
0#
#415000
b101001 1
b101000 5
b101000 :
b101000 ?
b100111 '
b10100111 $
b10100111 (
b10100111 ;
b10100111 @
1#
#420000
0#
#425000
b101010 1
b101001 5
b101001 :
b101001 ?
b101000 '
1#
#430000
0#
#435000
b101011 1
b101010 5
b101010 :
b101010 ?
b101001 '
b10011111 $
b10011111 (
b10011111 ;
b10011111 @
1#
#440000
0#
#445000
b101100 1
b101011 5
b101011 :
b101011 ?
b101010 '
b10010110 $
b10010110 (
b10010110 ;
b10010110 @
1#
#450000
0#
#455000
b101101 1
b101100 5
b101100 :
b101100 ?
b101011 '
1#
#460000
0#
#465000
b101110 1
b101101 5
b101101 :
b101101 ?
b101100 '
b10001101 $
b10001101 (
b10001101 ;
b10001101 @
1#
#470000
0#
#475000
b101111 1
b101110 5
b101110 :
b101110 ?
b101101 '
b10000100 $
b10000100 (
b10000100 ;
b10000100 @
1#
#480000
0#
#485000
b110000 1
b101111 5
b101111 :
b101111 ?
b101110 '
b1111011 $
b1111011 (
b1111011 ;
b1111011 @
1#
#490000
0#
#495000
b110001 1
b110000 5
b110000 :
b110000 ?
b101111 '
b1110011 $
b1110011 (
b1110011 ;
b1110011 @
1#
#500000
0#
#505000
b110010 1
b110001 5
b110001 :
b110001 ?
b110000 '
b1101010 $
b1101010 (
b1101010 ;
b1101010 @
1#
#510000
0#
#515000
b110011 1
b110010 5
b110010 :
b110010 ?
b110001 '
b100100 $
b100100 (
b100100 ;
b100100 @
1#
#520000
0#
#525000
b110100 1
b110011 5
b110011 :
b110011 ?
b110010 '
1#
#530000
0#
#535000
b110101 1
b110100 5
b110100 :
b110100 ?
b110011 '
1#
#540000
0#
#545000
b110110 1
b110101 5
b110101 :
b110101 ?
b110100 '
1#
#550000
0#
#555000
b110111 1
b110110 5
b110110 :
b110110 ?
b110101 '
1#
#560000
0#
#565000
b111000 1
b110111 5
b110111 :
b110111 ?
b110110 '
1#
#570000
0#
#575000
b111001 1
b111000 5
b111000 :
b111000 ?
b110111 '
1#
#580000
0#
#585000
b111010 1
b111001 5
b111001 :
b111001 ?
b111000 '
1#
#590000
0#
#595000
b111011 1
b111010 5
b111010 :
b111010 ?
b111001 '
1#
#600000
0#
#605000
b111100 1
b111011 5
b111011 :
b111011 ?
b111010 '
b101101 $
b101101 (
b101101 ;
b101101 @
1#
#610000
0#
#615000
b111101 1
b111100 5
b111100 :
b111100 ?
b111011 '
b110110 $
b110110 (
b110110 ;
b110110 @
1#
#620000
0#
#625000
b111110 1
b111101 5
b111101 :
b111101 ?
b111100 '
b111111 $
b111111 (
b111111 ;
b111111 @
1#
#630000
0#
#635000
b111111 1
b111110 5
b111110 :
b111110 ?
b111101 '
b101010 $
b101010 (
b101010 ;
b101010 @
1#
#640000
0#
#645000
b0 1
1+
b111111 5
b111111 :
b111111 ?
b111110 '
b110010 $
b110010 (
b110010 ;
b110010 @
1#
#650000
0#
#655000
1.
17
b1 1
0+
b0 5
b0 :
b0 ?
b111111 '
b111011 $
b111011 (
b111011 ;
b111011 @
1#
#660000
0#
#665000
1~
1V
1^
1k
1s
1{
1S
1[
1d
0f
1l
1n
1t
1v
1L
b111011 G
1T
b1110110 F
0'"
1h
0e
1p
0m
1x
0u
1P
1X
0&"
1K
1R
1b
1j
1r
1J
1Q
0#"
b0 *
b0 >
07
18
b10 1
b1 5
b1 :
b1 ?
b1011100 2
b1011100 I
b111011 3
b111011 B
b111011 E
b111011 4
b111011 A
b111011 D
b1000000 '
b1000100 $
b1000100 (
b1000100 ;
b1000100 @
1#
#670000
0#
#675000
1{
1t
1s
1g
1l
1'"
1c
1%"
1\
1k
1|
1O
1W
0V
1_
0^
b1111111 G
1d
0f
1o
0n
1w
0v
1!"
b10000000 F
0~
1C
0P
1M
0X
1U
1]
0h
1e
0p
1m
0x
1u
1}
0J
0Q
1Y
0a
0i
0q
1y
b1000100 4
b1000100 A
b1000100 D
b11 1
b10 5
b10 :
b10 ?
b1000001 '
b1001101 $
b1001101 (
b1001101 ;
b1001101 @
1#
#680000
0#
#685000
0O
0g
b10001000 F
1f
0C
1P
0M
1h
0e
1J
1a
b100100 *
b100100 >
b100 1
b11 5
b11 :
b11 ?
b1001101 4
b1001101 A
b1001101 D
b1000010 '
b1110011 $
b1110011 (
b1110011 ;
b1110011 @
1#
#690000
0#
#695000
0k
0d
0c
b1110011 G
0\
0W
1V
0_
1^
0g
1f
0o
0n
0w
b10101110 F
1v
1X
0U
0]
0h
1e
1p
0m
1x
0u
1Q
0Y
0a
1i
1q
b1110011 4
b1110011 A
b1110011 D
b101 1
b100 5
b100 :
b100 ?
b1000011 '
b1111011 $
b1111011 (
b1111011 ;
b1111011 @
1#
#700000
0#
#705000
1n
1k
b1111011 G
1d
b10110110 F
0f
1h
0e
1a
b110 1
b101 5
b101 :
b101 ?
b1111011 4
b1111011 A
b1111011 D
b1000100 '
b10000100 $
b10000100 (
b10000100 ;
b10000100 @
1#
#710000
0#
#715000
1{
1t
1s
1g
1l
1c
0%"
1\
1k
0|
0H
1O
1W
0V
1_
0^
b111111 G
1d
0f
1o
0n
1w
0v
0!"
1~
0("
b11000000 F
1'"
1C
0P
1M
0X
1U
1]
0h
1e
0p
1m
0x
1u
0}
1&"
0J
0Q
1Y
0a
0i
0q
0y
1#"
b10000100 4
b10000100 A
b10000100 D
b111 1
b110 5
b110 :
b110 ?
b1000101 '
b10001101 $
b10001101 (
b10001101 ;
b10001101 @
1#
#720000
0#
#725000
0O
0g
b11001000 F
1f
0C
1P
0M
1h
0e
1J
1a
b1000 1
b111 5
b111 :
b111 ?
b10001101 4
b10001101 A
b10001101 D
b1000110 '
b1101111 $
b1101111 (
b1101111 ;
b1101111 @
1#
#730000
0#
#735000
b1001 1
b1000 5
b1000 :
b1000 ?
b1000111 '
b1111000 $
b1111000 (
b1111000 ;
b1111000 @
1#
#740000
0#
#745000
b1010 1
b1001 5
b1001 :
b1001 ?
b1001000 '
b10000001 $
b10000001 (
b10000001 ;
b10000001 @
1#
#750000
0#
#755000
b1011 1
b1010 5
b1010 :
b1010 ?
b1001001 '
b10001001 $
b10001001 (
b10001001 ;
b10001001 @
1#
#760000
0#
#765000
b101101 *
b101101 >
b1100 1
b1011 5
b1011 :
b1011 ?
b1001010 '
b10110000 $
b10110000 (
b10110000 ;
b10110000 @
1#
#770000
0#
#775000
0k
0d
0c
b110011 G
0\
1O
0_
1^
0g
1f
0o
0n
0w
b11101100 F
1v
1C
0P
1M
0]
0h
1e
1p
0m
1x
0u
0J
0Y
0a
1i
1q
b10110000 4
b10110000 A
b10110000 D
b1101 1
b1100 5
b1100 :
b1100 ?
b1001011 '
1#
#780000
0#
#785000
b111111 *
b111111 >
b1110 1
b1101 5
b1101 :
b1101 ?
b1001100 '
b10111000 $
b10111000 (
b10111000 ;
b10111000 @
1#
#790000
0#
#795000
1n
1k
b111011 G
1d
b11110100 F
0f
1h
0e
1a
b10111000 4
b10111000 A
b10111000 D
b1111 1
b1110 5
b1110 :
b1110 ?
b1001101 '
1#
#800000
0#
#805000
b1010000 *
b1010000 >
b10000 1
b1111 5
b1111 :
b1111 ?
b1001110 '
b11000001 $
b11000001 (
b11000001 ;
b11000001 @
1#
#810000
0#
#815000
0{
0t
0s
0H
0l
0("
1'"
0%"
0k
0|
0O
b11 G
0d
1f
0o
1n
0w
1v
0!"
b11111100 F
1~
0C
1P
0M
0h
1e
0p
1m
0x
1u
1}
1J
0a
0i
0q
1y
b11000001 4
b11000001 A
b11000001 D
b10001 1
b10000 5
b10000 :
b10000 ?
b1001111 '
1#
#820000
0#
#825000
b1100010 *
b1100010 >
b10010 1
b10001 5
b10001 :
b10001 ?
b1010000 '
1#
#830000
0#
#835000
b10011 1
b10010 5
b10010 :
b10010 ?
b1010001 '
b10100011 $
b10100011 (
b10100011 ;
b10100011 @
1#
#840000
0#
#845000
b1101010 *
b1101010 >
b10100 1
b10011 5
b10011 :
b10011 ?
b1010010 '
1#
#850000
0#
#855000
b10101 1
b10100 5
b10100 :
b10100 ?
b1010011 '
1#
#860000
0#
#865000
b1111011 *
b1111011 >
b10110 1
b10101 5
b10101 :
b10101 ?
b1010100 '
1#
#870000
0#
#875000
b10111 1
b10110 5
b10110 :
b10110 ?
b1010101 '
b10111000 $
b10111000 (
b10111000 ;
b10111000 @
1#
#880000
0#
#885000
b10001101 *
b10001101 >
b11000 1
b10111 5
b10111 :
b10111 ?
b1010110 '
1#
#890000
0#
#895000
b11001 1
b11000 5
b11000 :
b11000 ?
b1010111 '
b10110000 $
b10110000 (
b10110000 ;
b10110000 @
1#
#900000
0#
#905000
b10010110 *
b10010110 >
b11010 1
b11001 5
b11001 :
b11001 ?
b1011000 '
1#
#910000
0#
